{"request":{"subject":"Print jobs stuck in print Queue","mode":{"name":"Chat","id":"4"},"group":{"name":"Printer Problems","id":"3"},"requester":{"email_id":"EMAILID","name":"EMAILID","is_vipuser":false,"id":"301"},"item":null,"level":{"name":"Tier 1","id": "1"},"service_category":{"name":"Hardware","id":"5" },"priority":{"name":"High","id":"4" },"subcategory":null,"status":{"name":"Open","id":"1"},"template":{"name":"Default Request","id":"4"},"email_ids_to_notify": ["hemamalini.n@inspirisys.com"], "request_type":{"name":"Incident","id":"1"},"description":"unable to print","technician":null,"category":{"name":"Printers","id":"6"}}}